ChangeLog.rst
LICENSE
MANIFEST.in
README.rst
setup.cfg
setup.py
cudnnenv/__init__.py
cudnnenv.egg-info/PKG-INFO
cudnnenv.egg-info/SOURCES.txt
cudnnenv.egg-info/dependency_links.txt
cudnnenv.egg-info/entry_points.txt
cudnnenv.egg-info/top_level.txt
test/test_command.py
test/test_util.py