Metadata-Version: 1.1
Name: cudnnenv
Version: 0.6.2
Summary: cudnn environment manager
Home-page: https://github.com/unnonouno/cudnnenv
Author: Yuya Unno
Author-email: unnonouno@gmail.com
License: MIT License
Platform: UNKNOWN
Classifier: Operating System :: POSIX :: Linux
Classifier: Operating System :: MacOS :: MacOS X
Classifier: Environment :: Console
Classifier: Programming Language :: Python
Classifier: License :: OSI Approved :: MIT License
Classifier: Development Status :: 2 - Pre-Alpha
Classifier: Intended Audience :: Information Technology
Classifier: Topic :: Utilities
